<?xml version="1.0" encoding="UTF-8"?>
<gresources>
  <gresource prefix="/com/github/kotontrion/kompass-bar">
    <file>style.css</file>
    <file preprocess="xml-stripblanks">ui/bar.ui</file>
    <file preprocess="xml-stripblanks">ui/qs.ui</file>
    <file preprocess="xml-stripblanks">ui/qsAudio.ui</file>
    <file preprocess="xml-stripblanks">ui/qsAudioEndpoint.ui</file>
    <file preprocess="xml-stripblanks">ui/qsBluetooth.ui</file>
    <file preprocess="xml-stripblanks">ui/qsBluetoothDevice.ui</file>
    <file preprocess="xml-stripblanks">ui/qsNotif.ui</file>
    <file preprocess="xml-stripblanks">ui/notification.ui</file>
    <file preprocess="xml-stripblanks">ui/mprisPlayer.ui</file>
    <file preprocess="xml-stripblanks">ui/launcher.ui</file>
    <file preprocess="xml-stripblanks">ui/appButton.ui</file>
    
    <file compressed="true">icons/symbolic/apps/arch-linux-rounded-symbolic.svg</file>
    <file compressed="true">icons/symbolic/apps/arch-linux-symbolic.svg</file>
  </gresource>
</gresources>
